amzurlog/__init__.py
amzurlog/comprehensive_demo.json
amzurlog/config.py
amzurlog/context.py
amzurlog/core.py
amzurlog/decorators.py
amzurlog/exception_configs.py
amzurlog/exception_handlers.py
amzurlog/exception_tracking.py
amzurlog/exceptions.py
amzurlog/filters.py
amzurlog/formatters.py
amzurlog/handlers.py
amzurlog/security_logs.json
amzurlog/sensitive_data.py
amzurlog/sensitive_formatters.py
amzurlog/specialized.py
amzurlog/specialized_decorators.py
amzurlog/streaming.py
amzurlog/streaming_configs.py
amzurlog/streaming_example.py
amzurlog/streaming_handlers.py
amzurlog-1.2.1.dist-info/licenses/LICENSE
amzurlog-1.2.1.dist-info/METADATA
amzurlog-1.2.1.dist-info/WHEEL
amzurlog-1.2.1.dist-info/entry_points.txt
amzurlog-1.2.1.dist-info/top_level.txt
amzurlog-1.2.1.dist-info/RECORD
