Metadata-Version: 2.4
Name: amzurlog
Version: 1.2.1
Summary: A powerful, flexible, and easy-to-use logging library with streaming and exception tracking
Home-page: https://github.com/Iswarya-Amzur/amzurlog
Author: AmzurATG
Author-email: AmzurATG <support@amzur.com>
License: MIT License
Project-URL: Homepage, https://github.com/Iswarya-Amzur/amzurlog
Project-URL: Documentation, https://github.com/Iswarya-Amzur/amzurlog/blob/main/README.md
Project-URL: Repository, https://github.com/Iswarya-Amzur/amzurlog.git
Project-URL: Bug Reports, https://github.com/Iswarya-Amzur/amzurlog/issues
Keywords: logging,monitoring,streaming,exceptions,elk,grafana,sentry
Classifier: Development Status :: 5 - Production/Stable
Classifier: Intended Audience :: Developers
Classifier: License :: OSI Approved :: MIT License
Classifier: Operating System :: OS Independent
Classifier: Programming Language :: Python :: 3
Classifier: Programming Language :: Python :: 3.7
Classifier: Programming Language :: Python :: 3.8
Classifier: Programming Language :: Python :: 3.9
Classifier: Programming Language :: Python :: 3.10
Classifier: Programming Language :: Python :: 3.11
Classifier: Programming Language :: Python :: 3.12
Classifier: Topic :: Software Development :: Libraries :: Python Modules
Classifier: Topic :: System :: Logging
Classifier: Topic :: System :: Monitoring
Classifier: Topic :: Software Development :: Debuggers
Requires-Python: >=3.7
License-File: LICENSE
Requires-Dist: typing-extensions>=3.7.4; python_version < "3.8"
Requires-Dist: elasticsearch<10.0.0,>=7.0.0
Requires-Dist: kafka-python<3.0.0,>=2.0.0
Requires-Dist: redis<7.0.0,>=4.0.0
Requires-Dist: requests<3.0.0,>=2.25.0
Requires-Dist: sentry-sdk<3.0.0,>=1.0.0
Requires-Dist: rollbar<2.0.0,>=0.16.0
Requires-Dist: psutil<6.0.0,>=5.0.0
Provides-Extra: minimal
Provides-Extra: streaming
Requires-Dist: elasticsearch>=7.0.0; extra == "streaming"
Requires-Dist: kafka-python>=2.0.0; extra == "streaming"
Requires-Dist: redis>=4.0.0; extra == "streaming"
Requires-Dist: requests>=2.25.0; extra == "streaming"
Provides-Extra: exceptions
Requires-Dist: sentry-sdk>=1.0.0; extra == "exceptions"
Requires-Dist: rollbar>=0.16.0; extra == "exceptions"
Provides-Extra: performance
Requires-Dist: psutil>=5.0.0; extra == "performance"
Provides-Extra: all
Requires-Dist: elasticsearch>=7.0.0; extra == "all"
Requires-Dist: kafka-python>=2.0.0; extra == "all"
Requires-Dist: redis>=4.0.0; extra == "all"
Requires-Dist: requests>=2.25.0; extra == "all"
Requires-Dist: sentry-sdk>=1.0.0; extra == "all"
Requires-Dist: rollbar>=0.16.0; extra == "all"
Requires-Dist: psutil>=5.0.0; extra == "all"
Provides-Extra: dev
Requires-Dist: pytest>=6.0; extra == "dev"
Requires-Dist: pytest-cov>=2.0; extra == "dev"
Requires-Dist: black>=21.0; extra == "dev"
Requires-Dist: flake8>=3.8; extra == "dev"
Requires-Dist: mypy>=0.800; extra == "dev"
Requires-Dist: twine>=3.0.0; extra == "dev"
Requires-Dist: wheel>=0.36.0; extra == "dev"
Requires-Dist: build>=0.7.0; extra == "dev"
Dynamic: author
Dynamic: home-page
Dynamic: license-file
Dynamic: requires-python
